streampipe/__init__.py
streampipe/streampipe.py
streampipe-0.1.dist-info/LICENSE.txt
streampipe-0.1.dist-info/METADATA
streampipe-0.1.dist-info/WHEEL
streampipe-0.1.dist-info/top_level.txt
streampipe-0.1.dist-info/RECORD
