Metadata-Version: 2.1
Name: streampipe
Version: 0.1
Summary: StreamPipe is a straightforward multi-worker pipeline for streaming data in Python.
Home-page: https://github.com/highvight/streampipe
Author: highvight
Author-email: adriankrueger@gmail.com
License: MIT
Platform: any
Classifier: Development Status :: 4 - Beta
Classifier: Programming Language :: Python
License-File: LICENSE.txt
Requires-Dist: importlib-metadata
Requires-Dist: seqqueue >=0.4
Provides-Extra: testing
Requires-Dist: setuptools ; extra == 'testing'
Requires-Dist: pytest ; extra == 'testing'
Requires-Dist: pytest-benchmark ; extra == 'testing'
